GeizhuiqiuLinghundeXiandairen/README.md
GeizhuiqiuLinghundeXiandairen/__init__.py
GeizhuiqiuLinghundeXiandairen/__main__.py
GeizhuiqiuLinghundeXiandairen/file.epub
GeizhuiqiuLinghundeXiandairen/index.html
GeizhuiqiuLinghundeXiandairen/css/__init__.py
GeizhuiqiuLinghundeXiandairen/css/annotations.css
GeizhuiqiuLinghundeXiandairen/css/main.css
GeizhuiqiuLinghundeXiandairen/css/normalize.css
GeizhuiqiuLinghundeXiandairen/css/popup.css
GeizhuiqiuLinghundeXiandairen/font/__init__.py
GeizhuiqiuLinghundeXiandairen/font/fontello.eot
GeizhuiqiuLinghundeXiandairen/font/fontello.svg
GeizhuiqiuLinghundeXiandairen/font/fontello.ttf
GeizhuiqiuLinghundeXiandairen/font/fontello.woff
GeizhuiqiuLinghundeXiandairen/img/__init__.py
GeizhuiqiuLinghundeXiandairen/img/annotator-glyph-sprite.png
GeizhuiqiuLinghundeXiandairen/img/annotator-icon-sprite.png
GeizhuiqiuLinghundeXiandairen/img/apple-touch-icon.png
GeizhuiqiuLinghundeXiandairen/img/cancelfullscreen.png
GeizhuiqiuLinghundeXiandairen/img/close.png
GeizhuiqiuLinghundeXiandairen/img/fullscreen.png
GeizhuiqiuLinghundeXiandairen/img/loader.gif
GeizhuiqiuLinghundeXiandairen/img/menu-icon.png
GeizhuiqiuLinghundeXiandairen/img/save.png
GeizhuiqiuLinghundeXiandairen/img/saved.png
GeizhuiqiuLinghundeXiandairen/img/settings-s.png
GeizhuiqiuLinghundeXiandairen/img/settings.png
GeizhuiqiuLinghundeXiandairen/img/star.png
GeizhuiqiuLinghundeXiandairen/js/__init__.py
GeizhuiqiuLinghundeXiandairen/js/epub.js
GeizhuiqiuLinghundeXiandairen/js/epub.min.js
GeizhuiqiuLinghundeXiandairen/js/epub.min.map
GeizhuiqiuLinghundeXiandairen/js/hooks.min.js
GeizhuiqiuLinghundeXiandairen/js/hooks.min.map
GeizhuiqiuLinghundeXiandairen/js/reader.js
GeizhuiqiuLinghundeXiandairen/js/reader.js.map
GeizhuiqiuLinghundeXiandairen/js/reader.min.js
GeizhuiqiuLinghundeXiandairen/js/reader.min.map
GeizhuiqiuLinghundeXiandairen/js/hooks/__init__.py
GeizhuiqiuLinghundeXiandairen/js/hooks/extensions/__init__.py
GeizhuiqiuLinghundeXiandairen/js/hooks/extensions/highlight.js
geizhuiqiu_linghunde_xiandairen-2022.10.3.0.dist-info/METADATA
geizhuiqiu_linghunde_xiandairen-2022.10.3.0.dist-info/WHEEL
geizhuiqiu_linghunde_xiandairen-2022.10.3.0.dist-info/entry_points.txt
geizhuiqiu_linghunde_xiandairen-2022.10.3.0.dist-info/top_level.txt
geizhuiqiu_linghunde_xiandairen-2022.10.3.0.dist-info/RECORD
